logconf.py
logconf-0.2.1.dist-info/LICENSE
logconf-0.2.1.dist-info/WHEEL
logconf-0.2.1.dist-info/METADATA
logconf-0.2.1.dist-info/RECORD
