Metadata-Version: 2.1
Name: logconf
Version: 0.2.1
Summary: convenient python stdlib logging configuration
Home-page: UNKNOWN
License: UNKOWN
Author: Andreas Lutro
Author-email: anlutro@gmail.com
Requires-Python: >=3.5,<4.0
Classifier: Programming Language :: Python :: 3
Classifier: Programming Language :: Python :: 3.5
Classifier: Programming Language :: Python :: 3.6
Classifier: Programming Language :: Python :: 3.7
